aimes_math/__init__.py
aimes_math/aimes_number.py
aimes_math/aimes_table.py
aimes_math/operations.py
aimes_math-0.0.2.dist-info/LICENSE
aimes_math-0.0.2.dist-info/METADATA
aimes_math-0.0.2.dist-info/WHEEL
aimes_math-0.0.2.dist-info/top_level.txt
aimes_math-0.0.2.dist-info/RECORD
